tanalyzer/__init__.py
tanalyzer/cli.py
tanalyzer/const.py
tanalyzer/schema.py
tanalyzer/twitter.py
tanalyzer/utils.py
twitter_analyzer-1.0.1.dist-info/METADATA
twitter_analyzer-1.0.1.dist-info/RECORD
twitter_analyzer-1.0.1.dist-info/WHEEL
twitter_analyzer-1.0.1.dist-info/entry_points.txt
twitter_analyzer-1.0.1.dist-info/top_level.txt
twitter_analyzer-1.0.1.dist-info/zip-safe
