Metadata-Version: 2.1
Name: twitter-analyzer
Version: 1.0.1
Summary: Analyze your twitter account
Home-page: https://github.com/vangheem/twitter-analyzer
Author: Nathan Van Gheem
Author-email: vangheem@gmail.com
License: BSD
Keywords: asyncio,twitter,sqlite
Platform: UNKNOWN
Classifier: License :: OSI Approved :: BSD License
Classifier: Intended Audience :: Developers
Classifier: Programming Language :: Python :: 3.5
Classifier: Programming Language :: Python :: 3.6
Classifier: Programming Language :: Python :: 3.7
Classifier: Topic :: Software Development :: Libraries :: Python Modules
Provides-Extra: test
Requires-Dist: aiohttp
Requires-Dist: python-dateutil
Requires-Dist: textblob
Requires-Dist: click
Requires-Dist: sqlalchemy
Requires-Dist: sqlalchemy-aio
Requires-Dist: peony-twitter[aiohttp]
Provides-Extra: test
Requires-Dist: pytest; extra == 'test'
Requires-Dist: pytest-asyncio (>=0.8.0); extra == 'test'
Requires-Dist: pytest-cov; extra == 'test'
Requires-Dist: coverage (>=4.0.3); extra == 'test'
